fuzentry/__init__.py
fuzentry/agents.py
fuzentry/auth.py
fuzentry/core.py
fuzentry/exporter.py
fuzentry/memory.py
fuzentry/plugins.py
fuzentry/prompts.py
fuzentry-0.1.0.dist-info/licenses/LICENSE
fuzentry-0.1.0.dist-info/METADATA
fuzentry-0.1.0.dist-info/WHEEL
fuzentry-0.1.0.dist-info/top_level.txt
fuzentry-0.1.0.dist-info/RECORD
