Metadata-Version: 2.4
Name: fuzentry
Version: 0.1.0
Summary: Official Python SDK for Fuzentry AI AgentOS PaaS Platform
Home-page: https://github.com/fuzentry/python-sdk
Author: Fuzentry
Author-email: Fuzentry <support@fuzentry.com>
License: Proprietary
Project-URL: Homepage, https://fuzentry.com
Project-URL: Documentation, https://docs.fuzentry.com
Project-URL: Repository, https://github.com/fuzentry/python-sdk
Project-URL: Bug Tracker, https://github.com/fuzentry/python-sdk/issues
Keywords: ai,agents,llm,orchestration,aws-marketplace,saas,sdk
Classifier: Development Status :: 4 - Beta
Classifier: Intended Audience :: Developers
Classifier: License :: Other/Proprietary License
Classifier: Programming Language :: Python :: 3
Classifier: Programming Language :: Python :: 3.8
Classifier: Programming Language :: Python :: 3.9
Classifier: Programming Language :: Python :: 3.10
Classifier: Programming Language :: Python :: 3.11
Classifier: Programming Language :: Python :: 3.12
Requires-Python: >=3.8
License-File: LICENSE
Requires-Dist: requests>=2.31.0
Provides-Extra: dev
Requires-Dist: pytest>=7.4.0; extra == "dev"
Requires-Dist: pytest-cov>=4.1.0; extra == "dev"
Requires-Dist: black>=23.7.0; extra == "dev"
Requires-Dist: mypy>=1.5.0; extra == "dev"
Requires-Dist: flake8>=6.1.0; extra == "dev"
Dynamic: author
Dynamic: home-page
Dynamic: license-file
Dynamic: requires-python
